accepts/__init__.py
stdin/__init__.py
accepts-2019.3.23.dist-info/METADATA
accepts-2019.3.23.dist-info/WHEEL
accepts-2019.3.23.dist-info/top_level.txt
accepts-2019.3.23.dist-info/RECORD
